frel/__init__.py
frel/main.py
frel/cli/commands/__init__.py
frel/cli/commands/_commands.py
frel/cli/models/__init__.py
frel/cli/models/_models.py
frel/cli/presenter/__init__.py
frel/cli/presenter/_fetch.py
frel/cli/presenter/_release.py
frel/fetch/__init__.py
frel/fetch/_fetcher.py
frel/fetch/_models.py
frel/gh/__init__.py
frel/gh/_connector.py
frel/gh/_models.py
frel-0.1.1.dist-info/METADATA
frel-0.1.1.dist-info/WHEEL
frel-0.1.1.dist-info/entry_points.txt
frel-0.1.1.dist-info/licenses/LICENSE
frel-0.1.1.dist-info/RECORD
