Metadata-Version: 2.3
Name: frel
Version: 0.1.1
Summary: Add your description here
Author-email: alexjuda <alexanderjuda@gmail.com>
License-File: LICENSE
Requires-Python: >=3.8
Requires-Dist: click>=8.1.7
Requires-Dist: humanize>=4.10.0
Requires-Dist: requests>=2.32.3
Requires-Dist: rich>=13.7.1
Provides-Extra: test
Requires-Dist: pytest>=8; extra == 'test'
